slenps/__init__.py
slenps/utils.py
slenps/version.py
slenps/eclusters/__init__.py
slenps/eclusters/cluster.py
slenps/eclusters/embedding.py
slenps/eclusters/embedding_models.py
slenps-0.1.3.dist-info/LICENSE
slenps-0.1.3.dist-info/METADATA
slenps-0.1.3.dist-info/WHEEL
slenps-0.1.3.dist-info/top_level.txt
slenps-0.1.3.dist-info/RECORD
