Metadata-Version: 2.1
Name: slenps
Version: 0.1.3
Summary: Some Pipelines
License: MIT License
Requires-Python: >=3.8
License-File: LICENSE
Requires-Dist: scipy <=1.12
Requires-Dist: numpy
Requires-Dist: pandas
Requires-Dist: gensim
Requires-Dist: psutil
Requires-Dist: scikit-learn
Requires-Dist: sentence-transformers
Requires-Dist: tqdm
Requires-Dist: umap-learn
Requires-Dist: torch
